setup.py
src/digimat/__init__.py
src/digimat.rws.egg-info/PKG-INFO
src/digimat.rws.egg-info/SOURCES.txt
src/digimat.rws.egg-info/dependency_links.txt
src/digimat.rws.egg-info/namespace_packages.txt
src/digimat.rws.egg-info/not-zip-safe
src/digimat.rws.egg-info/requires.txt
src/digimat.rws.egg-info/top_level.txt
src/digimat/rws/__init__.py
src/digimat/rws/rws.py