Metadata-Version: 1.0
Name: digimat.rws
Version: 0.1.5
Summary: Digimat RWS Client
Home-page: UNKNOWN
Author: Frederic Hess
Author-email: fhess@splust.ch
License: PSF
Platform: UNKNOWN
